data_designer/engine/__init__.py
data_designer/engine/_version.py
data_designer/engine/compiler.py
data_designer/engine/configurable_task.py
data_designer/engine/errors.py
data_designer/engine/model_provider.py
data_designer/engine/secret_resolver.py
data_designer/engine/validation.py
data_designer/engine/analysis/column_statistics.py
data_designer/engine/analysis/dataset_profiler.py
data_designer/engine/analysis/errors.py
data_designer/engine/analysis/column_profilers/base.py
data_designer/engine/analysis/column_profilers/judge_score_profiler.py
data_designer/engine/analysis/column_profilers/registry.py
data_designer/engine/analysis/utils/column_statistics_calculations.py
data_designer/engine/analysis/utils/judge_score_processing.py
data_designer/engine/column_generators/__init__.py
data_designer/engine/column_generators/registry.py
data_designer/engine/column_generators/generators/__init__.py
data_designer/engine/column_generators/generators/base.py
data_designer/engine/column_generators/generators/embedding.py
data_designer/engine/column_generators/generators/expression.py
data_designer/engine/column_generators/generators/llm_completion.py
data_designer/engine/column_generators/generators/samplers.py
data_designer/engine/column_generators/generators/seed_dataset.py
data_designer/engine/column_generators/generators/validation.py
data_designer/engine/column_generators/utils/errors.py
data_designer/engine/column_generators/utils/generator_classification.py
data_designer/engine/column_generators/utils/judge_score_factory.py
data_designer/engine/column_generators/utils/prompt_renderer.py
data_designer/engine/dataset_builders/artifact_storage.py
data_designer/engine/dataset_builders/column_wise_builder.py
data_designer/engine/dataset_builders/errors.py
data_designer/engine/dataset_builders/multi_column_configs.py
data_designer/engine/dataset_builders/utils/__init__.py
data_designer/engine/dataset_builders/utils/concurrency.py
data_designer_engine-0.4.0.dist-info/METADATA
data_designer_engine-0.4.0.dist-info/WHEEL
data_designer_engine-0.4.0.dist-info/RECORD
